setup.cfg
setup.py
PyPardot.egg-info/PKG-INFO
PyPardot.egg-info/SOURCES.txt
PyPardot.egg-info/dependency_links.txt
PyPardot.egg-info/top_level.txt
pypardot/__init__.py
pypardot/client.py
pypardot/errors.py
pypardot/objects/__init__.py
pypardot/objects/accounts.py
pypardot/objects/emails.py
pypardot/objects/lists.py
pypardot/objects/opportunities.py
pypardot/objects/prospects.py
pypardot/objects/users.py
pypardot/objects/visitoractivities.py
pypardot/objects/visitors.py
pypardot/objects/visits.py