Metadata-Version: 1.0
Name: PyPardot
Version: 0.1
Summary: API wrapper for Pardot marketing automation software.
Home-page: https://github.com/joshgeller/PyPardot
Author: Josh Geller
Author-email: joshualgeller@gmail.com
License: UNKNOWN
Keywords: pardot
Platform: UNKNOWN
